devbooster/__init__.py
devbooster/api/__init__.py
devbooster/api/main.py
devbooster/cli/__init__.py
devbooster/cli/app.py
devbooster/cli/commands/__init__.py
devbooster/cli/commands/generate.py
devbooster/config/__init__.py
devbooster/config/config_loader.py
devbooster/config_data/column_rules.txt
devbooster/config_data/pk_rules.txt
devbooster/config_data/prefix_rules.txt
devbooster/config_data/table_rules.txt
devbooster/config_data/table_whitelist.txt
devbooster/core/__init__.py
devbooster/core/ai_analyzer.py
devbooster/core/analyzer.py
devbooster/core/models.py
devbooster/core/parser.py
devbooster/core/renderer.py
devbooster/core/writer.py
devbooster/templates/egov/oracle/controller.java.j2
devbooster/templates/egov/oracle/mapper.java.j2
devbooster/templates/egov/oracle/mapper.xml.j2
devbooster/templates/egov/oracle/service.java.j2
devbooster/templates/egov/oracle/service_impl.java.j2
devbooster/templates/egov/oracle/vo.java.j2
devbooster-1.5.3.dist-info/licenses/LICENSE
devbooster-1.5.3.dist-info/METADATA
devbooster-1.5.3.dist-info/WHEEL
devbooster-1.5.3.dist-info/entry_points.txt
devbooster-1.5.3.dist-info/top_level.txt
devbooster-1.5.3.dist-info/RECORD
