Metadata-Version: 2.4
Name: devbooster
Version: 1.5.3
Summary: AI-powerd CRUD code generator for eGov Framework with intelligent PK analysis
Author: crazyBeerDwarf
License: MIT
Project-URL: Homepage, https://github.com/KTC-GIT/devbooster
Project-URL: Documentation, https://github.com/KTC-GIT/devbooster#readme
Project-URL: Repository, https://github.com/KTC-GIT/devbooster
Project-URL: Issues, https://github.com/KTC-GIT/devbooster/issues
Project-URL: changelog, https://github.com/KTC-GIT/devbooster/release
Keywords: egov,crud,generator,code-generator,전자정부프레임워크,ai,ollama,mybatis,spring
Classifier: Development Status :: 4 - Beta
Classifier: Intended Audience :: Developers
Classifier: Programming Language :: Python :: 3
Classifier: Programming Language :: Python :: 3.10
Classifier: Programming Language :: Python :: 3.11
Classifier: Programming Language :: Python :: 3.12
Classifier: Topic :: Software Development :: Code Generators
Classifier: Topic :: Software Development :: Libraries :: Python Modules
Classifier: Natural Language :: Korean
Classifier: Operating System :: OS Independent
Requires-Python: >=3.10
License-File: LICENSE
Requires-Dist: click>=8.1.0
Requires-Dist: pandas>=2.0.0
Requires-Dist: openpyxl>=3.1.0
Requires-Dist: jinja2>=3.1.0
Requires-Dist: python-multipart>=0.0.6
Requires-Dist: requests>=2.31.0
Provides-Extra: dev
Requires-Dist: pytest>=7.4.0; extra == "dev"
Requires-Dist: ruff>=0.1.0; extra == "dev"
Requires-Dist: black>=23.0.0; extra == "dev"
Requires-Dist: twine>=4.0.0; extra == "dev"
Requires-Dist: build>=1.0.0; extra == "dev"
Requires-Dist: fastapi>=0.104.0; extra == "dev"
Requires-Dist: uvicorn[standard]>=0.24.0; extra == "dev"
Dynamic: license-file
